{
  "generated_at": "2026-03-28T12:35:17.258840",
  "summary": {
    "high": 3,
    "elevated": 6,
    "normal": 20,
    "quiet": 25
  },
  "countries": {
    "Morocco": {
      "article_count": 4,
      "source_count": 1,
      "baseline": 4.2,
      "ratio": 0.96,
      "status": "normal",
      "confidence": "normal",
      "keywords": [
        {
          "word": "Guerre",
          "count": 1
        }
      ],
      "keyword_pairs": [],
      "articles": [
        {
          "title": "France-Maroc : ce que cinq siècles de diplomatie disent de la relation actuelle",
          "url": "https://www.jeuneafrique.com/1774716/politique/france-maroc-ce-que-cinq-siecles-de-diplomatie-disent-des-tensions-actuelles/",
          "source": "Jeune Afrique",
          "published": "2026-03-28T10:14:24",
          "lead": "Avec l’annonce du départ de Christophe Lecourtier, nommé à la tête de l’Agence française de développement, le sujet des "
        },
        {
          "title": "Nouvelle dette cachée au Sénégal, blocage du détroit d’Ormuz, narcos de Dubaï au Maroc… Les 5 infos qu’il ne fallait pas louper",
          "url": "https://www.jeuneafrique.com/1783677/politique/nouvelle-dette-cachee-au-senegal-blocage-du-detroit-dormuz-narcos-de-dubai-au-maroc-les-5-infos-quil-ne-fallait-pas-louper/",
          "source": "Jeune Afrique",
          "published": "2026-03-28T08:06:00",
          "lead": "Cette semaine, le Brief de Jeune Afrique revient sur les difficultés croissantes des entreprises africaines provoquées p"
        },
        {
          "title": "CAN 2025 : comment la CAF a déclaré le Sénégal perdant sans pour autant attribuer son titre au Maroc",
          "url": "https://www.jeuneafrique.com/1783711/politique/can-2025-comment-la-caf-a-declare-le-senegal-perdant-sans-pour-autant-attribuer-son-titre-au-maroc/",
          "source": "Jeune Afrique",
          "published": "2026-03-27T13:46:29",
          "lead": "En rendant une décision incohérente et jusqu’ici non motivée, la Commission d’appel de la Confédération africaine de foo"
        },
        {
          "title": "Rita Maria Zniber : « Au Maroc, comme sur l’ensemble du continent, le secteur agroalimentaire entre dans une phase de recomposition stratégique »",
          "url": "https://www.jeuneafrique.com/1783625/economie-entreprises/rita-maria-zniber-au-maroc-comme-sur-lensemble-du-continent-le-secteur-agroalimentaire-entre-dans-une-phase-de-recomposition-strategique/",
          "source": "Jeune Afrique",
          "published": "2026-03-27T12:38:44",
          "lead": "Souveraineté alimentaire, financement, gestion des ressources en eau… Pour la PDG du géant marocain Diana Holding, 2026 "
        }
      ],
      "sources": [
        "Jeune Afrique"
      ]
    },
    "Algeria": {
      "article_count": 1,
      "source_count": 1,
      "baseline": 1.6,
      "ratio": 0.64,
      "status": "normal",
      "confidence": "low",
      "keywords": [],
      "keyword_pairs": [],
      "articles": [
        {
          "title": "Pope Leo’s Africa tour sparks hope and controversy",
          "url": "http://www.africanews.com/2026/03/27/pope-leos-africa-tour-sparks-hope-and-controversy/",
          "source": "Africanews",
          "published": "2026-03-27T16:01:44",
          "lead": "As Pope Leo XIV prepares for his first major African trip next month, Algeria welcomes a historic papal debut while Equa"
        }
      ],
      "sources": [
        "Africanews"
      ]
    },
    "Tunisia": {
      "article_count": 3,
      "source_count": 1,
      "baseline": 1.1,
      "ratio": 2.81,
      "status": "elevated",
      "confidence": "low",
      "keywords": [
        {
          "word": "Sécheresse",
          "count": 1
        },
        {
          "word": "Élection",
          "count": 1
        },
        {
          "word": "Gouvernement",
          "count": 1
        }
      ],
      "keyword_pairs": [],
      "articles": [
        {
          "title": "Tunisie: le Désertif’action, à la recherche de solutions innovantes pour lutter contre la sécheresse",
          "url": "https://www.rfi.fr/fr/environnement/20260328-tunisie-le-d%C3%A9sertif-action-%C3%A0-la-recherche-de-solutions-innovantes-pour-lutter-contre-la-s%C3%A9cheresse",
          "source": "RFI Afrique",
          "published": "2026-03-28T08:45:41",
          "lead": "Le sixième sommet sur la désertification, le Désertif’action, s'achève ce 28 mars 2026 à Djerba en Tunisie. Organisé par"
        },
        {
          "title": "Tunisie: à Monastir, le congrès de l'UGTT veut marquer le renouveau de la centrale syndicale",
          "url": "https://www.rfi.fr/fr/afrique/20260328-tunisie-%C3%A0-monastir-le-congr%C3%A8s-de-l-ugtt-veut-marquer-le-renouveau-de-la-centrale-syndicale",
          "source": "RFI Afrique",
          "published": "2026-03-28T07:21:49",
          "lead": "En Tunisie, la puissante centrale syndicale l'UGTT a tenu son congrès électif dans la ville de Monastir, durant trois jo"
        },
        {
          "title": "En Tunisie, le réalisateur Nejib Belkadhi ressuscite l’émission mythique «Chems Allik»",
          "url": "https://www.rfi.fr/fr/podcasts/reportage-afrique/20260327-en-tunisie-le-r%C3%A9alisateur-nejib-belkadhi-ressuscite-l-%C3%A9mission-mythique-chems-allik",
          "source": "RFI Afrique",
          "published": "2026-03-27T23:04:36",
          "lead": "En Tunisie, le réalisateur et acteur Nejib Belkadhi a ressuscité l’émission Chems Allik, une émission phare des années 2"
        }
      ],
      "sources": [
        "RFI Afrique"
      ]
    },
    "Libya": {
      "article_count": 0,
      "source_count": 0,
      "baseline": 0.9,
      "ratio": 0.0,
      "status": "quiet",
      "confidence": "none",
      "keywords": [],
      "keyword_pairs": [],
      "articles": [],
      "sources": []
    },
    "Egypt": {
      "article_count": 2,
      "source_count": 2,
      "baseline": 1.1,
      "ratio": 1.76,
      "status": "elevated",
      "confidence": "medium",
      "keywords": [
        {
          "word": "War",
          "count": 1
        }
      ],
      "keyword_pairs": [],
      "articles": [
        {
          "title": "Curfews, EVs and ethanol: How African countries are trying to save fuel",
          "url": "http://www.africanews.com/2026/03/27/curfews-evs-and-ethanol-how-african-countries-are-trying-to-save-fuel/",
          "source": "Africanews",
          "published": "2026-03-27T15:53:36",
          "lead": "Egypt has ordered shops, restaurants and shopping malls to close from 9:00 pm from Saturday, hoping to curb energy bills"
        },
        {
          "title": "Africa: Afreximbank to Hold Its 33rd Annual Meetings in El Alamein, Egypt, From 21-24 June 2026",
          "url": "https://allafrica.com/stories/202603280063.html",
          "source": "AllAfrica",
          "published": "2026-03-28T08:45:02",
          "lead": "[Afreximbank] African Export-Import Bank (Afreximbank) has announced that it will hold its 33rd Annual Meetings (AAM2026"
        }
      ],
      "sources": [
        "AllAfrica",
        "Africanews"
      ]
    },
    "Sudan": {
      "article_count": 1,
      "source_count": 1,
      "baseline": 4.4,
      "ratio": 0.23,
      "status": "normal",
      "confidence": "low",
      "keywords": [
        {
          "word": "Rsf",
          "count": 1
        },
        {
          "word": "Guerre",
          "count": 1
        }
      ],
      "keyword_pairs": [],
      "articles": [
        {
          "title": "Dans l’est de la RDC, il est de plus en plus difficile d'exercer le métier de journaliste",
          "url": "https://www.rfi.fr/fr/podcasts/menaces-sur-l-information/20260328-dans-l-est-de-la-rdc-il-est-de-plus-en-plus-difficile-d-exercer-le-m%C3%A9tier-de-journaliste",
          "source": "RFI Afrique",
          "published": "2026-03-28T06:24:52",
          "lead": "L’ONG Reporters sans frontières (RSF) a publié, ce jeudi 26 mars, un rapport sur la pratique du journalisme dans la régi"
        }
      ],
      "sources": [
        "RFI Afrique"
      ]
    },
    "Mauritania": {
      "article_count": 0,
      "source_count": 0,
      "baseline": 0.8,
      "ratio": 0.0,
      "status": "quiet",
      "confidence": "none",
      "keywords": [],
      "keyword_pairs": [],
      "articles": [],
      "sources": []
    },
    "Mali": {
      "article_count": 2,
      "source_count": 2,
      "baseline": 2.7,
      "ratio": 0.74,
      "status": "normal",
      "confidence": "normal",
      "keywords": [
        {
          "word": "Crise",
          "count": 1
        }
      ],
      "keyword_pairs": [],
      "articles": [
        {
          "title": "Mali: à Mopti, l'arrivée de citernes soulage sans rassurer les habitants",
          "url": "https://www.rfi.fr/fr/afrique/20260327-mali-%C3%A0-mopti-l-arriv%C3%A9e-de-citernes-soulage-sans-rassurer-les-habitants",
          "source": "RFI Afrique",
          "published": "2026-03-27T14:46:02",
          "lead": "Au Mali, un convoi de camions citernes sous escorte militaire est arrivé le 26 mars au soir à Mopti. De quoi alléger la "
        },
        {
          "title": "Affaire Paramount au Mali : Boubou Cissé, ancien Premier ministre d’IBK, condamné à 20 ans de prison",
          "url": "https://www.jeuneafrique.com/1783788/politique/affaire-paramount-au-mali-boubou-cisse-ancien-premier-ministre-dibk-condamne-a-20-ans-de-prison/",
          "source": "Jeune Afrique",
          "published": "2026-03-27T17:14:02",
          "lead": "Plusieurs anciens ministres d’Ibrahim Boubacar Keïta (IBK), ainsi que des militaires, ont été reconnus coupables de déto"
        }
      ],
      "sources": [
        "RFI Afrique",
        "Jeune Afrique"
      ]
    },
    "Burkina Faso": {
      "article_count": 2,
      "source_count": 1,
      "baseline": 1.6,
      "ratio": 1.25,
      "status": "normal",
      "confidence": "normal",
      "keywords": [
        {
          "word": "Déplacés",
          "count": 1
        },
        {
          "word": "Humanitaire",
          "count": 1
        }
      ],
      "keyword_pairs": [],
      "articles": [
        {
          "title": "Le Burkina Faso adopte une «Charte de la révolution» qui redéfinit les règles de gouvernance dans le pays",
          "url": "https://www.rfi.fr/fr/afrique/20260328-le-burkina-faso-adopte-une-charte-de-la-r%C3%A9volution-qui-red%C3%A9finit-les-r%C3%A8gles-de-gouvernance-dans-le-pays",
          "source": "RFI Afrique",
          "published": "2026-03-28T04:00:47",
          "lead": "Le document, dont l'objectif est de permettre au pays de rompre avec les « modèles politiques impérialistes et néocoloni"
        },
        {
          "title": "Burkina: une ex-ministre condamnée à 5 ans de prison pour des détournements de fonds destinés aux déplacés",
          "url": "https://www.rfi.fr/fr/afrique/20260327-burkina-une-ex-ministre-condamn%C3%A9e-%C3%A0-5-ans-de-prison-pour-des-d%C3%A9tournements-de-fonds-destin%C3%A9s-aux-d%C3%A9plac%C3%A9s",
          "source": "RFI Afrique",
          "published": "2026-03-27T14:52:28",
          "lead": "Au Burkina Faso, Laure Zongo, ex-ministre de l'Action humanitaire, a été condamnée, vendredi 27 mars, à Ouagadougou pour"
        }
      ],
      "sources": [
        "RFI Afrique"
      ]
    },
    "Niger": {
      "article_count": 1,
      "source_count": 1,
      "baseline": 2.1,
      "ratio": 0.48,
      "status": "normal",
      "confidence": "low",
      "keywords": [],
      "keyword_pairs": [],
      "articles": [
        {
          "title": "Le Niger va créer des groupes civils « d’autodéfense » pour lutter contre le jihadisme",
          "url": "https://www.jeuneafrique.com/1784065/politique/le-niger-va-creer-des-groupes-civils-dautodefense-pour-lutter-contre-le-jihadisme/",
          "source": "Jeune Afrique",
          "published": "2026-03-28T11:01:45",
          "lead": "Le régime militaire du Niger a annoncé la création prochaine d’auxiliaires civils de l’armée pour combattre les groupes "
        }
      ],
      "sources": [
        "Jeune Afrique"
      ]
    },
    "Senegal": {
      "article_count": 8,
      "source_count": 3,
      "baseline": 5.8,
      "ratio": 1.38,
      "status": "normal",
      "confidence": "normal",
      "keywords": [
        {
          "word": "Président",
          "count": 2
        },
        {
          "word": "Guerre",
          "count": 1
        },
        {
          "word": "Protest",
          "count": 1
        },
        {
          "word": "War",
          "count": 1
        },
        {
          "word": "President",
          "count": 1
        },
        {
          "word": "Government",
          "count": 1
        }
      ],
      "keyword_pairs": [],
      "articles": [
        {
          "title": "Sénégal: l'UA refuse de soutenir la candidature de l'ex-président Macky Sall au poste de secrétaire général de l'ONU",
          "url": "https://www.rfi.fr/fr/afrique/20260327-s%C3%A9n%C3%A9gal-l-ua-refuse-de-soutenir-la-candidature-de-l-ex-pr%C3%A9sident-macky-sall-au-poste-de-secr%C3%A9taire-g%C3%A9n%C3%A9ral-de-l-onu",
          "source": "RFI Afrique",
          "published": "2026-03-27T23:19:44",
          "lead": "Présenté aux 55 États membres de l'organisation continentale ce vendredi 27 mars, le projet de décision a été retoqué pa"
        },
        {
          "title": "Dudu Sarr (Dakar Music Expo): «Il n'y a pas mieux que la musique pour rassembler»",
          "url": "https://www.rfi.fr/fr/podcasts/le-grand-invit%C3%A9-afrique/20260328-dudu-sarr-dakar-music-expo-il-n-y-a-pas-mieux-que-la-musique-pour-rassembler",
          "source": "RFI Afrique",
          "published": "2026-03-28T06:15:02",
          "lead": "Direction Dakar pour retrouver notre Grand invité Afrique ce samedi. La capitale sénégalaise est bercée ce week-end par "
        },
        {
          "title": "Football: en amical, le Sénégal se tourne vers le Pérou, sans tourner la page CAF",
          "url": "https://www.rfi.fr/fr/afrique-foot/20260327-football-en-amical-le-s%C3%A9n%C3%A9gal-se-tourne-vers-le-p%C3%A9rou-sans-tourner-la-page-caf",
          "source": "RFI Afrique",
          "published": "2026-03-27T19:07:01",
          "lead": "À la veille du match amical contre le Pérou au Stade de France ce samedi 28 mars, le Sénégal tente de se concentrer sur "
        },
        {
          "title": "Nouvelle dette cachée au Sénégal, blocage du détroit d’Ormuz, narcos de Dubaï au Maroc… Les 5 infos qu’il ne fallait pas louper",
          "url": "https://www.jeuneafrique.com/1783677/politique/nouvelle-dette-cachee-au-senegal-blocage-du-detroit-dormuz-narcos-de-dubai-au-maroc-les-5-infos-quil-ne-fallait-pas-louper/",
          "source": "Jeune Afrique",
          "published": "2026-03-28T08:06:00",
          "lead": "Cette semaine, le Brief de Jeune Afrique revient sur les difficultés croissantes des entreprises africaines provoquées p"
        },
        {
          "title": "L’Union africaine ne soutient pas la candidature de Macky Sall à l’ONU",
          "url": "https://www.jeuneafrique.com/1784018/politique/lunion-africaine-ne-soutient-pas-la-candidature-de-macky-sall-a-lonu/",
          "source": "Jeune Afrique",
          "published": "2026-03-27T18:59:26",
          "lead": "Les États membres de l’Union africaine (UA) ont refusé de soutenir la candidature de l’ex-président sénégalais pour remp"
        },
        {
          "title": "CAN 2025 : comment la CAF a déclaré le Sénégal perdant sans pour autant attribuer son titre au Maroc",
          "url": "https://www.jeuneafrique.com/1783711/politique/can-2025-comment-la-caf-a-declare-le-senegal-perdant-sans-pour-autant-attribuer-son-titre-au-maroc/",
          "source": "Jeune Afrique",
          "published": "2026-03-27T13:46:29",
          "lead": "En rendant une décision incohérente et jusqu’ici non motivée, la Commission d’appel de la Confédération africaine de foo"
        },
        {
          "title": "Demonstrators gather in Dakar to protest Iran war and show solidarity",
          "url": "http://www.africanews.com/2026/03/28/demonstrators-gather-in-dakar-to-protest-iran-war-and-show-solidarity/",
          "source": "Africanews",
          "published": "2026-03-28T09:52:05",
          "lead": "Dozens of demonstrators gathered in Dakar on Friday to protest the ongoing Iran war, voicing opposition to military acti"
        },
        {
          "title": "Senegal distances itself from AU support for Macky Sall at the UN",
          "url": "http://www.africanews.com/2026/03/28/senegal-distances-itself-from-au-support-for-macky-sall-at-the-un/",
          "source": "Africanews",
          "published": "2026-03-28T07:29:16",
          "lead": "The Permanent Mission of Senegal to the African Union informed the AU Commission on Friday that the Senegalese governmen"
        }
      ],
      "sources": [
        "Africanews",
        "RFI Afrique",
        "Jeune Afrique"
      ]
    },
    "Gambia": {
      "article_count": 0,
      "source_count": 0,
      "baseline": 0.5,
      "ratio": 0.0,
      "status": "quiet",
      "confidence": "none",
      "keywords": [],
      "keyword_pairs": [],
      "articles": [],
      "sources": []
    },
    "Guinea-Bissau": {
      "article_count": 0,
      "source_count": 0,
      "baseline": 0.5,
      "ratio": 0.0,
      "status": "quiet",
      "confidence": "none",
      "keywords": [],
      "keyword_pairs": [],
      "articles": [],
      "sources": []
    },
    "Guinea": {
      "article_count": 1,
      "source_count": 1,
      "baseline": 2.6,
      "ratio": 0.39,
      "status": "normal",
      "confidence": "low",
      "keywords": [
        {
          "word": "Gouvernement",
          "count": 1
        }
      ],
      "keyword_pairs": [],
      "articles": [
        {
          "title": "Guinée équatoriale : le gouvernement nie prélever des fonds sur salaire pour la visite du pape",
          "url": "https://www.jeuneafrique.com/1784068/politique/guinee-equatoriale-le-gouvernement-nie-prelever-des-fonds-sur-salaire-pour-la-visite-du-pape/",
          "source": "Jeune Afrique",
          "published": "2026-03-28T11:38:40",
          "lead": "Avant l’arrivée de Léon XIV à Malabo le 21 avril, les autorités de Guinée équatoriale ont pratiqué, en février, des rete"
        }
      ],
      "sources": [
        "Jeune Afrique"
      ]
    },
    "Sierra Leone": {
      "article_count": 0,
      "source_count": 0,
      "baseline": 0.7,
      "ratio": 0.0,
      "status": "quiet",
      "confidence": "none",
      "keywords": [],
      "keyword_pairs": [],
      "articles": [],
      "sources": []
    },
    "Liberia": {
      "article_count": 0,
      "source_count": 0,
      "baseline": 2.0,
      "ratio": 0.0,
      "status": "quiet",
      "confidence": "none",
      "keywords": [],
      "keyword_pairs": [],
      "articles": [],
      "sources": []
    },
    "Côte d'Ivoire": {
      "article_count": 2,
      "source_count": 2,
      "baseline": 1.9,
      "ratio": 1.03,
      "status": "normal",
      "confidence": "normal",
      "keywords": [
        {
          "word": "Élection",
          "count": 1
        },
        {
          "word": "Mort",
          "count": 1
        }
      ],
      "keyword_pairs": [],
      "articles": [
        {
          "title": "Côte d'Ivoire: le secrétaire exécutif du PDCI Calice Yapo jugé non coupable de «troubles à l’ordre public»",
          "url": "https://www.rfi.fr/fr/afrique/20260328-c%C3%B4te-d-ivoire-le-secr%C3%A9taire-ex%C3%A9cutif-du-pdci-calice-yapo-jug%C3%A9-non-coupable-de-troubles-%C3%A0-l-ordre-public",
          "source": "RFI Afrique",
          "published": "2026-03-28T04:01:35",
          "lead": "Rendu vendredi 27 mars, ce jugement va à l'encontre des réquisitions du parquet qui avait demandé 36 mois de prison avec"
        },
        {
          "title": "Houphouët-Boigny, en 1985 : « Comme les crocodiles de Yamoussoukro, je dors les yeux ouverts »",
          "url": "https://www.jeuneafrique.com/1725453/politique/houphouet-boigny-en-1985-comme-les-crocodiles-de-yamoussoukro-je-dors-les-yeux-ouverts/",
          "source": "Jeune Afrique",
          "published": "2026-03-28T11:41:23",
          "lead": "Son enfance, les libertés, la religion, la mort, l’argent, le football… Dans cette interview, réalisée par Abdelaziz Dah"
        }
      ],
      "sources": [
        "RFI Afrique",
        "Jeune Afrique"
      ]
    },
    "Ghana": {
      "article_count": 1,
      "source_count": 1,
      "baseline": 2.5,
      "ratio": 0.41,
      "status": "normal",
      "confidence": "low",
      "keywords": [
        {
          "word": "President",
          "count": 1
        },
        {
          "word": "Election",
          "count": 1
        }
      ],
      "keyword_pairs": [],
      "articles": [
        {
          "title": "UN’s landmark slavery ruling energises African Union’s fight for reparations",
          "url": "https://www.theguardian.com/news/2026/mar/27/un-slavery-ruling-african-union-reparations-slavery-analysis",
          "source": "The Guardian Africa",
          "published": "2026-03-27T13:07:22",
          "lead": "• UN votes to describe slave trade as ‘gravest crime against humanity’Despite resistance from states who had role in cha"
        }
      ],
      "sources": [
        "The Guardian Africa"
      ]
    },
    "Togo": {
      "article_count": 0,
      "source_count": 0,
      "baseline": 0.5,
      "ratio": 0.0,
      "status": "quiet",
      "confidence": "none",
      "keywords": [],
      "keyword_pairs": [],
      "articles": [],
      "sources": []
    },
    "Benin": {
      "article_count": 3,
      "source_count": 3,
      "baseline": 1.7,
      "ratio": 1.76,
      "status": "elevated",
      "confidence": "medium",
      "keywords": [
        {
          "word": "Guerre",
          "count": 1
        },
        {
          "word": "Minister",
          "count": 1
        }
      ],
      "keyword_pairs": [],
      "articles": [
        {
          "title": "Au Bénin, la fermeture de la réserve de la Pendjari fragilise toute la région",
          "url": "https://www.france24.com/fr/vid%C3%A9o/20260328-au-b%C3%A9nin-la-fermeture-de-la-r%C3%A9serve-de-la-pendjari-fragilise-toute-la-r%C3%A9gion",
          "source": "France24 Afrique",
          "published": "2026-03-28T12:25:29",
          "lead": "Le Sahel est la région la plus touchée au monde par le terrorisme, et les conséquences débordent sur les pays voisins. A"
        },
        {
          "title": "Nouvelle dette cachée au Sénégal, blocage du détroit d’Ormuz, narcos de Dubaï au Maroc… Les 5 infos qu’il ne fallait pas louper",
          "url": "https://www.jeuneafrique.com/1783677/politique/nouvelle-dette-cachee-au-senegal-blocage-du-detroit-dormuz-narcos-de-dubai-au-maroc-les-5-infos-quil-ne-fallait-pas-louper/",
          "source": "Jeune Afrique",
          "published": "2026-03-28T08:06:00",
          "lead": "Cette semaine, le Brief de Jeune Afrique revient sur les difficultés croissantes des entreprises africaines provoquées p"
        },
        {
          "title": "Rival presidential candidates on campaign trail in Benin",
          "url": "http://www.africanews.com/2026/03/27/rival-presidential-candidates-on-campaign-trail-in-benin/",
          "source": "Africanews",
          "published": "2026-03-27T21:36:07",
          "lead": "Incumbent finance minister Romuald Wadagni is a strong favourite to win against opposition candidate, Paul Hounkpé."
        }
      ],
      "sources": [
        "Africanews",
        "Jeune Afrique",
        "France24 Afrique"
      ]
    },
    "Nigeria": {
      "article_count": 2,
      "source_count": 2,
      "baseline": 8.4,
      "ratio": 0.24,
      "status": "normal",
      "confidence": "normal",
      "keywords": [],
      "keyword_pairs": [],
      "articles": [
        {
          "title": "Nigeria bets on UK port investment",
          "url": "https://www.dw.com/en/nigeria-bets-on-uk-port-investment/a-76567291?maca=en-rss-en-africa-8291-xml-mrss",
          "source": "DW Africa",
          "published": "2026-03-27T18:00:00",
          "lead": "There are high hopes for upgrades to the Apapa Quays and Tin Can Island ports. But concerns remain over corruption and l"
        },
        {
          "title": "Au Nigeria, la raffinerie d’Aliko Dangote tourne à plein régime, sur fond de pénuries",
          "url": "https://www.lemonde.fr/afrique/article/2026/03/28/au-nigeria-la-raffinerie-d-aliko-dangote-tourne-a-plein-regime-sur-fond-de-penuries_6675038_3212.html",
          "source": "Le Monde Afrique",
          "published": "2026-03-28T10:00:07",
          "lead": "La méga infrastructure construite en banlieue de Lagos par le milliardaire nigérian exporte désormais du carburant vers "
        }
      ],
      "sources": [
        "Le Monde Afrique",
        "DW Africa"
      ]
    },
    "Cape Verde": {
      "article_count": 0,
      "source_count": 0,
      "baseline": 0.5,
      "ratio": 0.0,
      "status": "quiet",
      "confidence": "none",
      "keywords": [],
      "keyword_pairs": [],
      "articles": [],
      "sources": []
    },
    "Chad": {
      "article_count": 0,
      "source_count": 0,
      "baseline": 1.1,
      "ratio": 0.0,
      "status": "quiet",
      "confidence": "none",
      "keywords": [],
      "keyword_pairs": [],
      "articles": [],
      "sources": []
    },
    "Cameroon": {
      "article_count": 1,
      "source_count": 1,
      "baseline": 2.5,
      "ratio": 0.4,
      "status": "normal",
      "confidence": "low",
      "keywords": [
        {
          "word": "Mort",
          "count": 1
        },
        {
          "word": "Élection",
          "count": 1
        },
        {
          "word": "Président",
          "count": 1
        }
      ],
      "keyword_pairs": [],
      "articles": [
        {
          "title": "Cameroun: interdiction des hommages à l’opposant Anicet Ekane, mort en détention",
          "url": "https://www.rfi.fr/fr/afrique/20260328-cameroun-interdiction-des-hommages-%C3%A0-l-opposant-anicet-ekane-mort-en-d%C3%A9tention",
          "source": "RFI Afrique",
          "published": "2026-03-28T10:49:49",
          "lead": "Au Cameroun, les autorités ont interrompu des cérémonies d’hommage à Anicet Ekane, dans la région de l'Ouest du pays, ce"
        }
      ],
      "sources": [
        "RFI Afrique"
      ]
    },
    "CAR": {
      "article_count": 1,
      "source_count": 1,
      "baseline": 1.4,
      "ratio": 0.7,
      "status": "normal",
      "confidence": "low",
      "keywords": [],
      "keyword_pairs": [],
      "articles": [
        {
          "title": "Investiture de Faustin-Archange Touadéra : qui sont les chefs d’État attendus ?",
          "url": "https://www.jeuneafrique.com/1783981/politique/investiture-de-faustin-archange-touadera-qui-sont-les-chefs-detat-attendus/",
          "source": "Jeune Afrique",
          "published": "2026-03-27T19:00:55",
          "lead": "Près de trois mois après avoir été proclamé vainqueur de la présidentielle, Faustin-Archange Touadéra sera officiellemen"
        }
      ],
      "sources": [
        "Jeune Afrique"
      ]
    },
    "South Sudan": {
      "article_count": 0,
      "source_count": 0,
      "baseline": 1.9,
      "ratio": 0.0,
      "status": "quiet",
      "confidence": "none",
      "keywords": [],
      "keyword_pairs": [],
      "articles": [],
      "sources": []
    },
    "Eq. Guinea": {
      "article_count": 2,
      "source_count": 2,
      "baseline": 0.5,
      "ratio": 4.0,
      "status": "high",
      "confidence": "medium",
      "keywords": [
        {
          "word": "Gouvernement",
          "count": 1
        }
      ],
      "keyword_pairs": [],
      "articles": [
        {
          "title": "Guinée équatoriale : le gouvernement nie prélever des fonds sur salaire pour la visite du pape",
          "url": "https://www.jeuneafrique.com/1784068/politique/guinee-equatoriale-le-gouvernement-nie-prelever-des-fonds-sur-salaire-pour-la-visite-du-pape/",
          "source": "Jeune Afrique",
          "published": "2026-03-28T11:38:40",
          "lead": "Avant l’arrivée de Léon XIV à Malabo le 21 avril, les autorités de Guinée équatoriale ont pratiqué, en février, des rete"
        },
        {
          "title": "Pope Leo’s Africa tour sparks hope and controversy",
          "url": "http://www.africanews.com/2026/03/27/pope-leos-africa-tour-sparks-hope-and-controversy/",
          "source": "Africanews",
          "published": "2026-03-27T16:01:44",
          "lead": "As Pope Leo XIV prepares for his first major African trip next month, Algeria welcomes a historic papal debut while Equa"
        }
      ],
      "sources": [
        "Africanews",
        "Jeune Afrique"
      ]
    },
    "Gabon": {
      "article_count": 2,
      "source_count": 1,
      "baseline": 1.2,
      "ratio": 1.62,
      "status": "elevated",
      "confidence": "low",
      "keywords": [],
      "keyword_pairs": [],
      "articles": [
        {
          "title": "Gabon’s tiny turtles race against extinction as funding for protection dries up",
          "url": "http://www.africanews.com/2026/03/27/gabons-tiny-turtles-race-against-extinction-as-funding-for-protection-dries-up/",
          "source": "Africanews",
          "published": "2026-03-27T22:55:47",
          "lead": "Gabon is intensifying efforts to protect vulnerable sea turtle hatchlings as nesting season peaks between December and M"
        },
        {
          "title": "Gabon's eco-rangers battle to help threatened baby sea turtles survive",
          "url": "http://www.africanews.com/2026/03/27/gabons-eco-rangers-battle-to-help-threatened-baby-sea-turtles-survive/",
          "source": "Africanews",
          "published": "2026-03-27T15:29:03",
          "lead": "In addition to predators like crabs and bird, nests are threatened by coastal erosion and human activities like plastic "
        }
      ],
      "sources": [
        "Africanews"
      ]
    },
    "Congo": {
      "article_count": 0,
      "source_count": 0,
      "baseline": 2.2,
      "ratio": 0.0,
      "status": "quiet",
      "confidence": "none",
      "keywords": [],
      "keyword_pairs": [],
      "articles": [],
      "sources": []
    },
    "DRC": {
      "article_count": 6,
      "source_count": 4,
      "baseline": 7.0,
      "ratio": 0.86,
      "status": "normal",
      "confidence": "normal",
      "keywords": [
        {
          "word": "Rsf",
          "count": 1
        },
        {
          "word": "Guerre",
          "count": 1
        },
        {
          "word": "Gouvernement",
          "count": 1
        }
      ],
      "keyword_pairs": [],
      "articles": [
        {
          "title": "Dans l’est de la RDC, il est de plus en plus difficile d'exercer le métier de journaliste",
          "url": "https://www.rfi.fr/fr/podcasts/menaces-sur-l-information/20260328-dans-l-est-de-la-rdc-il-est-de-plus-en-plus-difficile-d-exercer-le-m%C3%A9tier-de-journaliste",
          "source": "RFI Afrique",
          "published": "2026-03-28T06:24:52",
          "lead": "L’ONG Reporters sans frontières (RSF) a publié, ce jeudi 26 mars, un rapport sur la pratique du journalisme dans la régi"
        },
        {
          "title": "RDC: une vidéo d’une femme maltraitée par un médecin juste après un accouchement provoque l’émoi",
          "url": "https://www.rfi.fr/fr/afrique/20260327-rdc-une-vid%C3%A9o-d-une-femme-maltrait%C3%A9e-par-un-m%C3%A9decin-juste-apr%C3%A8s-un-accouchement-provoque-l-%C3%A9moi",
          "source": "RFI Afrique",
          "published": "2026-03-27T14:37:12",
          "lead": "En République démocratique du Congo (RDC), une vidéo diffusée sur les réseaux sociaux a provoqué une vive émotion. On y "
        },
        {
          "title": "RD Congo: une vidéo virale souligne un problème de prise en charge de la santé des femmes",
          "url": "https://www.france24.com/fr/vid%C3%A9o/20260328-rd-congo-une-vid%C3%A9o-virale-souligne-un-probl%C3%A8me-de-prise-en-charge-de-la-sant%C3%A9-des-femmes",
          "source": "France24 Afrique",
          "published": "2026-03-28T11:28:17",
          "lead": "Une vidéo qui montre des violences sur une femme qui vient d'accoucher est devenue virale sur les réseaux sociaux en RD "
        },
        {
          "title": "L’UE ne financera la force rwandaise déployée au Mozambique contre les djihadistes affiliés à l’Etat islamique",
          "url": "https://www.lemonde.fr/afrique/article/2026/03/27/l-ue-coupe-le-financement-de-la-force-rwandaise-deployee-au-mozambique-contre-les-djihadistes-affilies-a-l-etat-islamique_6674572_3212.html",
          "source": "Le Monde Afrique",
          "published": "2026-03-27T14:30:09",
          "lead": "Les Etats européens excluent l’idée de reconduire une troisième fois l’aide de 20 millions d’euros à l’armée de Kigali, "
        },
        {
          "title": "À Washington, la paix entre le Rwanda et la RDC à l’épreuve du terrain",
          "url": "https://www.jeuneafrique.com/1773372/politique/a-washington-la-paix-entre-le-rwanda-et-la-rdc-a-lepreuve-du-terrain/",
          "source": "Jeune Afrique",
          "published": "2026-03-28T07:55:00",
          "lead": "Quatre mois après la signature d’un accord entre Paul Kagame et Félix Tshisekedi, la paix, vantée par Donald Trump, tard"
        },
        {
          "title": "En RDC, l’Église sera-t-elle la gardienne de la Constitution ?",
          "url": "https://www.jeuneafrique.com/1783800/politique/en-rdc-leglise-sera-t-elle-la-gardienne-de-la-constitution/",
          "source": "Jeune Afrique",
          "published": "2026-03-27T17:58:33",
          "lead": "Alors que la majorité formée autour de Félix Tshisekedi ne cache plus son intention de toucher à la Loi fondamentale, le"
        }
      ],
      "sources": [
        "RFI Afrique",
        "Jeune Afrique",
        "France24 Afrique",
        "Le Monde Afrique"
      ]
    },
    "São Tomé": {
      "article_count": 0,
      "source_count": 0,
      "baseline": 0.5,
      "ratio": 0.0,
      "status": "quiet",
      "confidence": "none",
      "keywords": [],
      "keyword_pairs": [],
      "articles": [],
      "sources": []
    },
    "Angola": {
      "article_count": 0,
      "source_count": 0,
      "baseline": 0.5,
      "ratio": 0.0,
      "status": "quiet",
      "confidence": "none",
      "keywords": [],
      "keyword_pairs": [],
      "articles": [],
      "sources": []
    },
    "Eritrea": {
      "article_count": 0,
      "source_count": 0,
      "baseline": 0.5,
      "ratio": 0.0,
      "status": "quiet",
      "confidence": "none",
      "keywords": [],
      "keyword_pairs": [],
      "articles": [],
      "sources": []
    },
    "Djibouti": {
      "article_count": 2,
      "source_count": 2,
      "baseline": 0.5,
      "ratio": 4.0,
      "status": "high",
      "confidence": "medium",
      "keywords": [
        {
          "word": "Guerre",
          "count": 1
        }
      ],
      "keyword_pairs": [],
      "articles": [
        {
          "title": "Un navire transportant plus de 320 migrants fait naufrage au large de Djibouti",
          "url": "https://www.rfi.fr/fr/afrique/20260328-un-navire-transportant-plus-de-320-migrants-fait-naufrage-au-large-de-djibouti",
          "source": "RFI Afrique",
          "published": "2026-03-28T04:01:51",
          "lead": "Le drame, qui s'est déroulé dans la nuit du mardi 24 au mercredi 25 mars, a fait au moins neuf morts et 45 disparus, sel"
        },
        {
          "title": "Guerre en Iran : la présence américaine en Afrique face aux risques de représailles",
          "url": "https://www.jeuneafrique.com/1775707/politique/guerre-en-iran-la-presence-americaine-en-afrique-face-aux-risques-de-represailles/",
          "source": "Jeune Afrique",
          "published": "2026-03-28T12:31:45",
          "lead": "Sans donner de détails, Washington prend au sérieux les menaces qui pèsent sur ses ressortissants comme sur ses installa"
        }
      ],
      "sources": [
        "RFI Afrique",
        "Jeune Afrique"
      ]
    },
    "Ethiopia": {
      "article_count": 1,
      "source_count": 1,
      "baseline": 2.2,
      "ratio": 0.46,
      "status": "normal",
      "confidence": "low",
      "keywords": [
        {
          "word": "Crise",
          "count": 1
        },
        {
          "word": "Guerre",
          "count": 1
        }
      ],
      "keyword_pairs": [],
      "articles": [
        {
          "title": "«Cette crise me fait peur»: en Éthiopie, des chauffeurs démunis face aux prix des carburants",
          "url": "https://www.rfi.fr/fr/afrique/20260327-cette-crise-me-fait-peur-en-%C3%A9thiopie-des-chauffeurs-d%C3%A9munis-face-aux-prix-des-carburants",
          "source": "RFI Afrique",
          "published": "2026-03-27T15:12:41",
          "lead": "Le 16 mars dernier, le Premier ministre Abiy Ahmed a appelé à utiliser le carburant « avec parcimonie », craignant des p"
        }
      ],
      "sources": [
        "RFI Afrique"
      ]
    },
    "Somalia": {
      "article_count": 0,
      "source_count": 0,
      "baseline": 1.7,
      "ratio": 0.0,
      "status": "quiet",
      "confidence": "none",
      "keywords": [],
      "keyword_pairs": [],
      "articles": [],
      "sources": []
    },
    "Uganda": {
      "article_count": 1,
      "source_count": 1,
      "baseline": 2.2,
      "ratio": 0.46,
      "status": "normal",
      "confidence": "low",
      "keywords": [
        {
          "word": "Rsf",
          "count": 1
        },
        {
          "word": "Guerre",
          "count": 1
        }
      ],
      "keyword_pairs": [],
      "articles": [
        {
          "title": "Dans l’est de la RDC, il est de plus en plus difficile d'exercer le métier de journaliste",
          "url": "https://www.rfi.fr/fr/podcasts/menaces-sur-l-information/20260328-dans-l-est-de-la-rdc-il-est-de-plus-en-plus-difficile-d-exercer-le-m%C3%A9tier-de-journaliste",
          "source": "RFI Afrique",
          "published": "2026-03-28T06:24:52",
          "lead": "L’ONG Reporters sans frontières (RSF) a publié, ce jeudi 26 mars, un rapport sur la pratique du journalisme dans la régi"
        }
      ],
      "sources": [
        "RFI Afrique"
      ]
    },
    "Kenya": {
      "article_count": 2,
      "source_count": 1,
      "baseline": 6.1,
      "ratio": 0.33,
      "status": "normal",
      "confidence": "normal",
      "keywords": [
        {
          "word": "Rsf",
          "count": 1
        },
        {
          "word": "Guerre",
          "count": 1
        }
      ],
      "keyword_pairs": [],
      "articles": [
        {
          "title": "Dans l’est de la RDC, il est de plus en plus difficile d'exercer le métier de journaliste",
          "url": "https://www.rfi.fr/fr/podcasts/menaces-sur-l-information/20260328-dans-l-est-de-la-rdc-il-est-de-plus-en-plus-difficile-d-exercer-le-m%C3%A9tier-de-journaliste",
          "source": "RFI Afrique",
          "published": "2026-03-28T06:24:52",
          "lead": "L’ONG Reporters sans frontières (RSF) a publié, ce jeudi 26 mars, un rapport sur la pratique du journalisme dans la régi"
        },
        {
          "title": "Kenya: l'enquête se développe après la découverte d'une mystérieuse fosse commune",
          "url": "https://www.rfi.fr/fr/afrique/20260328-kenya-l-enqu%C3%AAte-se-d%C3%A9veloppe-apr%C3%A8s-la-d%C3%A9couverte-d-une-myst%C3%A9rieuse-fosse-commune",
          "source": "RFI Afrique",
          "published": "2026-03-28T06:10:26",
          "lead": "Au Kenya, les autopsies des dépouilles de Kericho, se poursuivent. Une fosse commune a été découverte - le week-end pass"
        }
      ],
      "sources": [
        "RFI Afrique"
      ]
    },
    "Rwanda": {
      "article_count": 4,
      "source_count": 3,
      "baseline": 2.6,
      "ratio": 1.56,
      "status": "elevated",
      "confidence": "medium",
      "keywords": [
        {
          "word": "Rsf",
          "count": 1
        },
        {
          "word": "Guerre",
          "count": 1
        }
      ],
      "keyword_pairs": [],
      "articles": [
        {
          "title": "Rwanda: la Cour suprême rejette le recours de l'opposante Victoire Ingabire",
          "url": "https://www.rfi.fr/fr/afrique/20260328-rwanda-la-cour-supr%C3%AAme-rejette-le-recours-de-l-opposante-victoire-ingabire",
          "source": "RFI Afrique",
          "published": "2026-03-28T06:55:05",
          "lead": "Au Rwanda, la Cour suprême rejette, ce vendredi 27 mars 2026, le recours en justice de Victoire Ingabire. La défense de "
        },
        {
          "title": "Dans l’est de la RDC, il est de plus en plus difficile d'exercer le métier de journaliste",
          "url": "https://www.rfi.fr/fr/podcasts/menaces-sur-l-information/20260328-dans-l-est-de-la-rdc-il-est-de-plus-en-plus-difficile-d-exercer-le-m%C3%A9tier-de-journaliste",
          "source": "RFI Afrique",
          "published": "2026-03-28T06:24:52",
          "lead": "L’ONG Reporters sans frontières (RSF) a publié, ce jeudi 26 mars, un rapport sur la pratique du journalisme dans la régi"
        },
        {
          "title": "L’UE ne financera la force rwandaise déployée au Mozambique contre les djihadistes affiliés à l’Etat islamique",
          "url": "https://www.lemonde.fr/afrique/article/2026/03/27/l-ue-coupe-le-financement-de-la-force-rwandaise-deployee-au-mozambique-contre-les-djihadistes-affilies-a-l-etat-islamique_6674572_3212.html",
          "source": "Le Monde Afrique",
          "published": "2026-03-27T14:30:09",
          "lead": "Les Etats européens excluent l’idée de reconduire une troisième fois l’aide de 20 millions d’euros à l’armée de Kigali, "
        },
        {
          "title": "À Washington, la paix entre le Rwanda et la RDC à l’épreuve du terrain",
          "url": "https://www.jeuneafrique.com/1773372/politique/a-washington-la-paix-entre-le-rwanda-et-la-rdc-a-lepreuve-du-terrain/",
          "source": "Jeune Afrique",
          "published": "2026-03-28T07:55:00",
          "lead": "Quatre mois après la signature d’un accord entre Paul Kagame et Félix Tshisekedi, la paix, vantée par Donald Trump, tard"
        }
      ],
      "sources": [
        "RFI Afrique",
        "Jeune Afrique",
        "Le Monde Afrique"
      ]
    },
    "Burundi": {
      "article_count": 3,
      "source_count": 2,
      "baseline": 1.1,
      "ratio": 2.81,
      "status": "high",
      "confidence": "medium",
      "keywords": [
        {
          "word": "Président",
          "count": 1
        },
        {
          "word": "Rsf",
          "count": 1
        },
        {
          "word": "Guerre",
          "count": 1
        },
        {
          "word": "Violence",
          "count": 1
        }
      ],
      "keyword_pairs": [],
      "articles": [
        {
          "title": "Sénégal: l'UA refuse de soutenir la candidature de l'ex-président Macky Sall au poste de secrétaire général de l'ONU",
          "url": "https://www.rfi.fr/fr/afrique/20260327-s%C3%A9n%C3%A9gal-l-ua-refuse-de-soutenir-la-candidature-de-l-ex-pr%C3%A9sident-macky-sall-au-poste-de-secr%C3%A9taire-g%C3%A9n%C3%A9ral-de-l-onu",
          "source": "RFI Afrique",
          "published": "2026-03-27T23:19:44",
          "lead": "Présenté aux 55 États membres de l'organisation continentale ce vendredi 27 mars, le projet de décision a été retoqué pa"
        },
        {
          "title": "Dans l’est de la RDC, il est de plus en plus difficile d'exercer le métier de journaliste",
          "url": "https://www.rfi.fr/fr/podcasts/menaces-sur-l-information/20260328-dans-l-est-de-la-rdc-il-est-de-plus-en-plus-difficile-d-exercer-le-m%C3%A9tier-de-journaliste",
          "source": "RFI Afrique",
          "published": "2026-03-28T06:24:52",
          "lead": "L’ONG Reporters sans frontières (RSF) a publié, ce jeudi 26 mars, un rapport sur la pratique du journalisme dans la régi"
        },
        {
          "title": "The Loss of a Journalist in Burundi",
          "url": "https://www.hrw.org/news/2026/03/27/the-loss-of-a-journalist-in-burundi",
          "source": "Human Rights Watch",
          "published": "2026-03-27T19:26:37",
          "lead": "Human Rights Watch mourns the&nbsp;passing of Burundian journalist Jackson Bahati, who died suddenly at age 55 on March "
        }
      ],
      "sources": [
        "RFI Afrique",
        "Human Rights Watch"
      ]
    },
    "Tanzania": {
      "article_count": 2,
      "source_count": 2,
      "baseline": 1.0,
      "ratio": 2.0,
      "status": "elevated",
      "confidence": "medium",
      "keywords": [
        {
          "word": "Rsf",
          "count": 1
        },
        {
          "word": "Guerre",
          "count": 1
        },
        {
          "word": "Killed",
          "count": 1
        }
      ],
      "keyword_pairs": [],
      "articles": [
        {
          "title": "Dans l’est de la RDC, il est de plus en plus difficile d'exercer le métier de journaliste",
          "url": "https://www.rfi.fr/fr/podcasts/menaces-sur-l-information/20260328-dans-l-est-de-la-rdc-il-est-de-plus-en-plus-difficile-d-exercer-le-m%C3%A9tier-de-journaliste",
          "source": "RFI Afrique",
          "published": "2026-03-28T06:24:52",
          "lead": "L’ONG Reporters sans frontières (RSF) a publié, ce jeudi 26 mars, un rapport sur la pratique du journalisme dans la régi"
        },
        {
          "title": "Tanzania landslides kill 20 as heavy rains hit East Africa",
          "url": "http://www.africanews.com/2026/03/27/tanzania-landslides-kill-20-as-heavy-rains-hit-east-africa/",
          "source": "Africanews",
          "published": "2026-03-27T20:13:10",
          "lead": "At least 20 people have been killed in landslides in southern Tanzania after days of intense rainfall, as extreme weathe"
        }
      ],
      "sources": [
        "Africanews",
        "RFI Afrique"
      ]
    },
    "Madagascar": {
      "article_count": 1,
      "source_count": 1,
      "baseline": 1.7,
      "ratio": 0.59,
      "status": "normal",
      "confidence": "low",
      "keywords": [],
      "keyword_pairs": [],
      "articles": [
        {
          "title": "Justice à Madagascar: faute de moyens, de nombreux mineurs toujours placés en détention",
          "url": "https://www.rfi.fr/fr/afrique/20260328-justice-%C3%A0-madagascar-faute-de-moyens-de-nombreux-mineurs-toujours-plac%C3%A9s-en-d%C3%A9tention",
          "source": "RFI Afrique",
          "published": "2026-03-28T12:13:42",
          "lead": "Magistrats, responsables du ministère de la Justice, associations… À Madagascar, un séminaire national vient de réunir, "
        }
      ],
      "sources": [
        "RFI Afrique"
      ]
    },
    "Comoros": {
      "article_count": 0,
      "source_count": 0,
      "baseline": 0.5,
      "ratio": 0.0,
      "status": "quiet",
      "confidence": "none",
      "keywords": [],
      "keyword_pairs": [],
      "articles": [],
      "sources": []
    },
    "Mauritius": {
      "article_count": 0,
      "source_count": 0,
      "baseline": 0.5,
      "ratio": 0.0,
      "status": "quiet",
      "confidence": "none",
      "keywords": [],
      "keyword_pairs": [],
      "articles": [],
      "sources": []
    },
    "Seychelles": {
      "article_count": 0,
      "source_count": 0,
      "baseline": 0.5,
      "ratio": 0.0,
      "status": "quiet",
      "confidence": "none",
      "keywords": [],
      "keyword_pairs": [],
      "articles": [],
      "sources": []
    },
    "Zambia": {
      "article_count": 0,
      "source_count": 0,
      "baseline": 0.5,
      "ratio": 0.0,
      "status": "quiet",
      "confidence": "none",
      "keywords": [],
      "keyword_pairs": [],
      "articles": [],
      "sources": []
    },
    "Malawi": {
      "article_count": 0,
      "source_count": 0,
      "baseline": 0.6,
      "ratio": 0.0,
      "status": "quiet",
      "confidence": "none",
      "keywords": [],
      "keyword_pairs": [],
      "articles": [],
      "sources": []
    },
    "Mozambique": {
      "article_count": 1,
      "source_count": 1,
      "baseline": 0.9,
      "ratio": 1.07,
      "status": "normal",
      "confidence": "low",
      "keywords": [],
      "keyword_pairs": [],
      "articles": [
        {
          "title": "L’UE ne financera la force rwandaise déployée au Mozambique contre les djihadistes affiliés à l’Etat islamique",
          "url": "https://www.lemonde.fr/afrique/article/2026/03/27/l-ue-coupe-le-financement-de-la-force-rwandaise-deployee-au-mozambique-contre-les-djihadistes-affilies-a-l-etat-islamique_6674572_3212.html",
          "source": "Le Monde Afrique",
          "published": "2026-03-27T14:30:09",
          "lead": "Les Etats européens excluent l’idée de reconduire une troisième fois l’aide de 20 millions d’euros à l’armée de Kigali, "
        }
      ],
      "sources": [
        "Le Monde Afrique"
      ]
    },
    "Zimbabwe": {
      "article_count": 0,
      "source_count": 0,
      "baseline": 2.3,
      "ratio": 0.0,
      "status": "quiet",
      "confidence": "none",
      "keywords": [],
      "keyword_pairs": [],
      "articles": [],
      "sources": []
    },
    "Namibia": {
      "article_count": 0,
      "source_count": 0,
      "baseline": 0.9,
      "ratio": 0.0,
      "status": "quiet",
      "confidence": "none",
      "keywords": [],
      "keyword_pairs": [],
      "articles": [],
      "sources": []
    },
    "Botswana": {
      "article_count": 0,
      "source_count": 0,
      "baseline": 0.5,
      "ratio": 0.0,
      "status": "quiet",
      "confidence": "none",
      "keywords": [],
      "keyword_pairs": [],
      "articles": [],
      "sources": []
    },
    "South Africa": {
      "article_count": 2,
      "source_count": 1,
      "baseline": 14.7,
      "ratio": 0.14,
      "status": "normal",
      "confidence": "normal",
      "keywords": [],
      "keyword_pairs": [],
      "articles": [
        {
          "title": "Global mohair supply flourishes in South Africa's desert",
          "url": "http://www.africanews.com/2026/03/27/global-mohair-supply-flourishes-in-south-africas-desert/",
          "source": "Africanews",
          "published": "2026-03-27T17:18:33",
          "lead": "Linked by dirt tracks and dotted with remote farms, the sparsely populated Karoo region sits at the heart of the global "
        },
        {
          "title": "Proposed anti-crime wall along Cape Town highway divides residents",
          "url": "http://www.africanews.com/2026/03/27/proposed-anti-crime-wall-along-cape-town-highway-divides-residents/",
          "source": "Africanews",
          "published": "2026-03-27T13:45:44",
          "lead": "There has been a surge in attacks along the multi-lane road which links the airport to the city centre."
        }
      ],
      "sources": [
        "Africanews"
      ]
    },
    "Eswatini": {
      "article_count": 0,
      "source_count": 0,
      "baseline": 0.5,
      "ratio": 0.0,
      "status": "quiet",
      "confidence": "none",
      "keywords": [],
      "keyword_pairs": [],
      "articles": [],
      "sources": []
    },
    "Lesotho": {
      "article_count": 0,
      "source_count": 0,
      "baseline": 0.5,
      "ratio": 0.0,
      "status": "quiet",
      "confidence": "none",
      "keywords": [],
      "keyword_pairs": [],
      "articles": [],
      "sources": []
    }
  }
}